README.md
setup.py
src/ebnf/__init__.py
src/ebnf/dialect.py
src/ebnf/ebnf.py
src/ebnf/railroad.py
src/ebnf.egg-info/PKG-INFO
src/ebnf.egg-info/SOURCES.txt
src/ebnf.egg-info/dependency_links.txt
src/ebnf.egg-info/requires.txt
src/ebnf.egg-info/top_level.txt
src/ebnf/dialects/__init__.py
src/ebnf/dialects/lark.py