Metadata-Version: 2.1
Name: ebnf
Version: 0.1.0
Summary: A collection of ebnf tools
Home-page: https://github.com/MegaIng/ebnf
Author: MegaIng
Author-email: trampchamp@hotmail.com
License: UNKNOWN
Project-URL: Bug Reports, https://github.com/MegaIng/ebnf/issues
Project-URL: Source, https://github.com/MegaIng/ebnf
Keywords: ebnf,grammars,tools,railroad,lark
Platform: UNKNOWN
Classifier: Development Status :: 2 - Pre-Alpha
Classifier: Intended Audience :: Developers
Classifier: Topic :: Software Development :: Build Tools
Classifier: Topic :: Documentation
Classifier: Topic :: Utilities
Classifier: Topic :: Text Processing
Classifier: License :: OSI Approved :: MIT License
Classifier: Programming Language :: Python :: 3
Classifier: Programming Language :: Python :: 3.9
Classifier: Programming Language :: Python :: 3 :: Only
Classifier: Typing :: Typed
Requires-Python: >=3.9
Provides-Extra: railroad
